{
    "multipart": [
        {   "when": { "age": 0 },
            "apply": { "model": "dynamictreescuisine:fruit/mandarin_age0" }
        },
        {   "when": { "age": 1 },
            "apply": [
                { "model": "dynamictreescuisine:fruit/mandarin_age1" },
                { "model": "dynamictreescuisine:fruit/mandarin_age1", "y": 90 },
                { "model": "dynamictreescuisine:fruit/mandarin_age1", "y": 180 },
                { "model": "dynamictreescuisine:fruit/mandarin_age1", "y": 270 }
            ]
        },
        {   "when": { "age": 2 },
            "apply": [
                { "model": "dynamictreescuisine:fruit/mandarin_age2" },
                { "model": "dynamictreescuisine:fruit/mandarin_age2", "y": 90 },
                { "model": "dynamictreescuisine:fruit/mandarin_age2", "y": 180 },
                { "model": "dynamictreescuisine:fruit/mandarin_age2", "y": 270 }
            ]
        },
        {   "when": { "age": 3 },
            "apply": [
                { "model": "dynamictreescuisine:fruit/mandarin_age3" },
                { "model": "dynamictreescuisine:fruit/mandarin_age3", "y": 90 },
                { "model": "dynamictreescuisine:fruit/mandarin_age3", "y": 180 },
                { "model": "dynamictreescuisine:fruit/mandarin_age3", "y": 270 }
            ]
        }
    ]
}