{"stat.chestOpened":11,"stat.walkOneCm":37141,"stat.pickup.minecraft.stick":3,"stat.pickup.forestry.sapling":1,"stat.useItem.forestry.grafter_proven":1,"stat.mineBlock.forestry.leaves":1,"stat.useItem.dynamictreesforestry.wengeseed":1,"stat.damageTaken":20,"stat.pickup.forestry.logs.1":9,"stat.pickup.dynamictreesforestry.wengeseed":7,"stat.pickup.forestry.logs.6":28,"stat.flyOneCm":294248,"stat.useItem.dynamictreesforestry.ipeseed":1,"stat.jump":618,"stat.swimOneCm":412,"stat.playOneMinute":35625,"stat.fallOneCm":1287,"stat.climbOneCm":3533,"stat.sneakTime":1014,"stat.crouchOneCm":4059,"stat.timeSinceDeath":35625,"stat.pickup.dynamictreesforestry.ipeseed":11,"stat.sprintOneCm":65648,"stat.useItem.minecraft.stone_slab2":254,"stat.diveOneCm":347}