{"stat.flyOneCm":17426,"stat.walkOneCm":6097,"stat.pickup.aether.skyroot_log":21,"stat.pickup.dynamictreestheaether2.holidayseed":1,"stat.useItem.dynamictreestheaether2.holidayseed":3,"stat.useItem.dynamictreestheaether2.amberootseed":2,"stat.jump":13,"stat.pickup.aether.skyroot_stick":7,"stat.playOneMinute":4926,"stat.sneakTime":293,"stat.damageDealt":10,"stat.crouchOneCm":540,"stat.timeSinceDeath":4926,"stat.sprintOneCm":2683,"stat.useItem.minecraft.stone_slab2":17,"stat.pickup.dynamictreestheaether2.amberootseed":5}