{"stat.flyOneCm":44079,"stat.pickup.tconstruct.slime_congealed":2,"stat.walkOneCm":10856,"stat.jump":55,"stat.playOneMinute":4741,"stat.pickup.integrateddynamics.menril_berries":25,"stat.pickup.minecraft.stick":2,"stat.pickup.integrateddynamics.menril_log":3,"stat.leaveGame":1,"stat.sneakTime":256,"stat.crouchOneCm":445,"stat.timeSinceDeath":4741,"stat.pickup.tconstruct.edible":1,"stat.sprintOneCm":7876,"stat.pickup.dynamictreesexc.menrilseed":5,"stat.useItem.minecraft.stone_slab2":8,"stat.pickup.integrateddynamics.crystalized_menril_chunk":4}